aiolambda/__init__.py
aiolambda/app.py
aiolambda/config.py
aiolambda/db.py
aiolambda/errors.py
aiolambda/logger.py
aiolambda/mq.py
aiolambda/security.py
aiolambda/typing.py
aiolambda-0.3.1.data/scripts/aiolambda-cli
aiolambda_cli/__init__.py
aiolambda_cli/check.py
aiolambda_cli/file.py
aiolambda_cli/path.py
aiolambda_cli/templates.py
aiolambda_cli/templates/.coveragerc.j2
aiolambda_cli/templates/.gitignore.j2
aiolambda_cli/templates/.travis.yml.j2
aiolambda_cli/templates/Dockerfile.j2
aiolambda_cli/templates/Makefile.j2
aiolambda_cli/templates/README.md.j2
aiolambda_cli/templates/requirements.txt.j2
aiolambda_cli/templates/requirements_test.txt.j2
aiolambda_cli/templates/tox.ini.j2
aiolambda_cli/templates/__PROJECT_NAME__/__init__.py.j2
aiolambda_cli/templates/__PROJECT_NAME__/__main__.py.j2
aiolambda_cli/templates/__PROJECT_NAME__/config.py.j2
aiolambda_cli/templates/__PROJECT_NAME__/db.py.j2
aiolambda_cli/templates/__PROJECT_NAME__/handlers.py.j2
aiolambda_cli/templates/__PROJECT_NAME__/main.py.j2
aiolambda_cli/templates/__PROJECT_NAME__/mq.py.j2
aiolambda_cli/templates/__PROJECT_NAME__/response.py.j2
aiolambda_cli/templates/docs/api/v1/openapi.yaml.j2
aiolambda_cli/templates/test/__init__.py.j2
aiolambda_cli/templates/test/test_db.py.j2
aiolambda_cli/templates/test/test_handlers.py.j2
aiolambda-0.3.1.dist-info/LICENSE
aiolambda-0.3.1.dist-info/METADATA
aiolambda-0.3.1.dist-info/WHEEL
aiolambda-0.3.1.dist-info/top_level.txt
aiolambda-0.3.1.dist-info/RECORD
