Metadata-Version: 2.1
Name: aiolambda
Version: 0.3.1
Summary: Python async microservices fasts!
Home-page: http://github.com/pando85/aiolambda
Author: Pando85
Author-email: pand855@gmail.com
License: GPLv3+
Keywords: aiolambda asyncio aiohttp asyncpg aio-pika
Platform: UNKNOWN
Classifier: Development Status :: 3 - Alpha
Classifier: License :: OSI Approved :: GNU General Public License (GPL)
Classifier: Programming Language :: Python :: 3.7
Classifier: Topic :: Internet :: WWW/HTTP :: HTTP Servers
Classifier: Intended Audience :: Developers
Requires-Dist: aiofunctools (==0.0.2)
Requires-Dist: asyncpg (==0.19.0)
Requires-Dist: cchardet (==2.1.4)
Requires-Dist: passlib (==1.7.1)
Requires-Dist: uvloop (==0.13.0)
Requires-Dist: aio-pika (==6.3.0)
Requires-Dist: docopt (==0.6.2)
Requires-Dist: Jinja2 (==2.10.3)
Requires-Dist: pathlib (==1.0.1)
Requires-Dist: connexion (==2.4.0)
Requires-Dist: toolz (==0.10.0)
